Workbook

Sheet Productos
A1: SKU | B1: Nombre | C1: Categorias | D1: SubCat1 | E1: Foto(s) | F1: Stock | G1: Precio | H1: Padre Id | I1: Hijo Id
A2: 04.08.0014-RJ | B2: 04.08.0014-RJ - CABLE UNILAY THHN ROJO # 14 100MTS ELECTROCABLE | C2: Material Eléctrico | D2: Cables | E2: https://res.cloudinary.com/riqra/image/upload/v1629483021/sellers/megaproductos/products/kt3wq49hob2irnir24dr.png | F2: 0 | G2: 33.67 | H2: =VLOOKUP(C2,Categorias!B:C,2,FALSE) -> 694 | I2: =VLOOKUP(D2,SubCategorias!B:C,2,FALSE) -> 1
A3: 110006209 | B3: 110006209 - CERAMICA PISO BOTTICCINO HUESO SEMI/MATE 45X45 (2.03) PL10 CELIMA | C3: Acabados | D3: Ceramica de piso | E3: https://res.cloudinary.com/riqra/image/upload/v1628261474/sellers/megaproductos/products/ftrgirohhrzto4ytborg.png | F3: 0 | G3: 8.64 | H3: =VLOOKUP(C3,Categorias!B:C,2,FALSE) -> 690 | I3: =VLOOKUP(D3,SubCategorias!B:C,2,FALSE) -> 0
A4: 111000 | B4: 111000 - SIKA 2 DE 2KG | C4: Construcción | D4: Impermeabilizantes | E4: https://res.cloudinary.com/riqra/image/upload/v1629394482/sellers/megaproductos/products/f0zwcp1b3amfoyblvpqh.png | F4: 22 | G4: 11.10 | H4: =VLOOKUP(C4,Categorias!B:C,2,FALSE) -> 703 | I4: =VLOOKUP(D4,SubCategorias!B:C,2,FALSE) -> 0
A5: 123662 | B5: 123662 - EMPASTE INTERIOR BLANCO 10KG + RESINA SIKA | C5: Pinturas y complementos | D5: Empastes | E5: https://res.cloudinary.com/riqra/image/upload/v1628722030/sellers/megaproductos/products/nwqsemsiv9mzvbj7zeaj.png | F5: 0 | G5: 9.35 | H5: =VLOOKUP(C5,Categorias!B:C,2,FALSE) -> 705 | I5: =VLOOKUP(D5,SubCategorias!B:C,2,FALSE) -> 0
A6: 15000102 | B6: 15000102 - INCASOLD #6 ROJO 100MTS INCABLE | C6: Material Eléctrico | D6: Cables | E6: https://res.cloudinary.com/riqra/image/upload/v1629739414/sellers/megaproductos/products/zg0ayfy9sxmajitvfxss.png | F6: 0 | G6: 248.67 | H6: =VLOOKUP(C6,Categorias!B:C,2,FALSE) -> 694 | I6: =VLOOKUP(D6,SubCategorias!B:C,2,FALSE) -> 1
A7: 15000201 | B7: 15000201 - INCASOLD #4 NEGRO 100MTS INCABLE | C7: Material Eléctrico | D7: Cables | E7: https://res.cloudinary.com/riqra/image/upload/v1629739392/sellers/megaproductos/products/og7vycn18wpmodimyxpw.png | F7: 1 | G7: 397.87 | H7: =VLOOKUP(C7,Categorias!B:C,2,FALSE) -> 694 | I7: =VLOOKUP(D7,SubCategorias!B:C,2,FALSE) -> 1
A8: 20021002118 | B8: 20021002118 - BROCHA MULTIUSO 6" WILSON | C8: Pinturas y complementos | D8: Brochas | E8: https://res.cloudinary.com/riqra/image/upload/v1628721066/sellers/megaproductos/products/y190zexeog3be27mbuwn.png | F8: 0 | G8: 11.91 | H8: =VLOOKUP(C8,Categorias!B:C,2,FALSE) -> 705 | I8: =VLOOKUP(D8,SubCategorias!B:C,2,FALSE) -> 0
A9: 23200101-NE | B9: 23200101-NE - CABLE FLEXIBLE #14 THHN/THWN NEGRO 100MTS INCABLE | C9: Material Eléctrico | D9: Cables | E9: https://res.cloudinary.com/riqra/image/upload/v1629738506/sellers/megaproductos/products/efjkcwpriklzifaii6gy.png | F9: 238 | G9: 32.95 | H9: =VLOOKUP(C9,Categorias!B:C,2,FALSE) -> 694 | I9: =VLOOKUP(D9,SubCategorias!B:C,2,FALSE) -> 1
A10: 4010146503 | B10: 4010146503 - GUANTES MASTER REVESTIDO NARANJA CORRUGADO T/M | C10: Seguridad Industrial | D10: Guantes | E10: https://res.cloudinary.com/riqra/image/upload/v1629739993/sellers/megaproductos/products/hzo5mt2bdu2bw25ytk1w.png | F10: 102 | G10: 2.58 | H10: =VLOOKUP(C10,Categorias!B:C,2,FALSE) -> 704 | I10: =VLOOKUP(D10,SubCategorias!B:C,2,FALSE) -> 0
A11: 44900701 | B11: 44900701 - CABLE CONCENTRICO THHN 2X14 100MTS INCABLE | C11: Material Eléctrico | D11: Otros | E11: https://res.cloudinary.com/riqra/image/upload/v1629738163/sellers/megaproductos/products/n83k8deaovil3wscwuib.png | F11: 3 | G11: 87.15 | H11: =VLOOKUP(C11,Categorias!B:C,2,FALSE) -> 694 | I11: =VLOOKUP(D11,SubCategorias!B:C,2,FALSE) -> 0
A12: OSP-200 | B12: OSP-200 - ABRAZADERA DE UN HUECO 2" EMT" | C12: Material Eléctrico | D12: Tubería Conduit Metálica (EMT) | E12: https://res.cloudinary.com/riqra/image/upload/v1629483480/sellers/megaproductos/products/v5ougnf9ssd5llkh9s3g.png | F12: 1525 | G12: 0.38 | H12: =VLOOKUP(C12,Categorias!B:C,2,FALSE) -> 694 | I12: =VLOOKUP(D12,SubCategorias!B:C,2,FALSE) -> 0
A13: TC0409 | B13: TC0409 - PALA CARBONERA C/MANGO CORTO TOOLCRAFT | C13: Herramientas Manuales | D13: Palas | E13: https://res.cloudinary.com/riqra/image/upload/v1629413504/sellers/megaproductos/products/clnnnfvkb96i8k7w9jys.png | F13: 0 | G13: 11.10 | H13: =VLOOKUP(C13,Categorias!B:C,2,FALSE) -> 741 | I13: =VLOOKUP(D13,SubCategorias!B:C,2,FALSE) -> 0
... A4673: 9.04E+05 | B4673: 903916E0 - CABO IDEAL 9/16 AZUL C/C (17KG APROX) PLASTIEMPAQUES | C4673: Ferretería | D4673: Cabos|Ferretería | E4673: https://res.cloudinary.com/riqra/image/upload/v1635877143/sellers/10/yjk5pyjumi7rg1bolgsa.png|https://res.cloudinary.com/riqra/image/upload/v1635877118/sellers/7/qmmck65lphnvqur2pmzj.png|https://res.cloudinary.com/riqra/image/upload/v1635877143/sellers/11/najqurzx50iqixwk9wcu.png | F4673: 5.22 | G4673: 5.09 | H4673: =VLOOKUP(C4673,Categorias!B:C,2,FALSE) -> 742 | I4673: =VLOOKUP(D4673,SubCategorias!B:C,2,FALSE) -> 0
A4674: 7.86E+12 | B4674: 7860693724204 - # BROCHA PRIMA 1" WILSON | E4674: https://res.cloudinary.com/riqra/image/upload/v1534706090/saas/resources/placeholders/product.png|https://res.cloudinary.com/riqra/image/upload/v1534706090/saas/resources/placeholders/product.png|https://res.cloudinary.com/riqra/image/upload/v1534706090/saas/resources/placeholders/product.png|https://res.cloudinary.com/riqra/image/upload/v1534706090/saas/resources/placeholders/product.png|https://res.cloudinary.com/riqra/image/upload/v1534706090/saas/resources/placeholders/product.png|https://res.cloudinary.com/riqra/image/upload/v1534706090/saas/resources/placeholders/product.png|https://res.cloudinary.com/riqra/image/upload/v1534706090/saas/resources/placeholders/product.png|https://res.cloudinary.com/riqra/image/upload/v1534706090/saas/resources/placeholders/product.png|https://res.cloudinary.com/riqra/image/upload/v1534706090/saas/resources/placeholders/product.png|https://res.cloudinary.com/riqra/image/upload/v1534706090/saas/resources/placeholders/product.png|https://res.cloudinary.com/riqra/image/upload/v1534706090/saas/resources/placeholders/product.png|https://res.cloudinary.com/riqra/image/upload/v1534706090/saas/resources/placeholders/product.png|https://res.cloudinary.com/riqra/image/upload/v1534706090/saas/resources/placeholders/product.png|https://res.cloudinary.com/riqra/image/upload/v1534706090/saas/resources/placeholders/product.png|https://res.cloudinary.com/riqra/image/upload/v1534706090/saas/resources/placeholders/product.png|https://res.cloudinary.com/riqra/image/upload/v1534706090/saas/resources/placeholders/product.png|https://res.cloudinary.com/riqra/image/upload/v1534706090/saas/resources/placeholders/product.png|https://res.cloudinary.com/riqra/image/upload/v1534706090/saas/resources/placeholders/product.png|https://res.cloudinary.com/riqra/image/upload/v1534706090/saas/resources/placeholders/product.png|https://res.cloudinary.com/riqra/image/upload/v1534706090/saas/resources/placeholders/product.png|https://res.cloudinary.com/riqra/image/upload/v1534706090/saas/resources/placeholders/product.png|https://res.cloudinary.com/riqra/image/upload/v1534706090/saas/resources/placeholders/product.png | F4674: 246 | G4674: 2.72 | H4674: =VLOOKUP(C4674,Categorias!B:C,2,FALSE) -> #N/A | I4674: =VLOOKUP(D4674,SubCategorias!B:C,2,FALSE) -> #N/A
A4675: 9.03E+12 | B4675: 9031040000000 - # CABO IDEAL AZUL 1/4. C/C (17KG APROX) PLASTIEMPAQUES | E4675: https://res.cloudinary.com/riqra/image/upload/v1534706090/saas/resources/placeholders/product.png | F4675: 0 | G4675: 4.27 | H4675: =VLOOKUP(C4675,Categorias!B:C,2,FALSE) -> #N/A | I4675: =VLOOKUP(D4675,SubCategorias!B:C,2,FALSE) -> #N/A
A4676: 9.04E+12 | B4676: 9035160000000 - CABO IDEAL AZUL 5/16. C/C (17KG APROX) PLASTIEMPAQUES | E4676: https://res.cloudinary.com/riqra/image/upload/v1534706090/saas/resources/placeholders/product.png | F4676: 32.5 | G4676: 4.27 | H4676: =VLOOKUP(C4676,Categorias!B:C,2,FALSE) -> #N/A | I4676: =VLOOKUP(D4676,SubCategorias!B:C,2,FALSE) -> #N/A
A4677: 0189/B3CR | B4677: 0189/B3 CR - JUEGO MONOCOMANDO FLOW (B3) PARA BIDET FV | E4677: https://res.cloudinary.com/riqra/image/upload/v1534706090/saas/resources/placeholders/product.png | F4677: 0 | G4677: 118.12 | H4677: =VLOOKUP(C4677,Categorias!B:C,2,FALSE) -> #N/A | I4677: =VLOOKUP(D4677,SubCategorias!B:C,2,FALSE) -> #N/A
A4678: 0600.13.BBR | B4678: 0600.13.B BR - VALVULA COMPUERTA (ESCLUSA) BR 1/2" FV | E4678: https://res.cloudinary.com/riqra/image/upload/v1534706090/saas/resources/placeholders/product.png | F4678: 319 | G4678: 8.51 | H4678: =VLOOKUP(C4678,Categorias!B:C,2,FALSE) -> #N/A | I4678: =VLOOKUP(D4678,SubCategorias!B:C,2,FALSE) -> #N/A
A4679: 0600.19.BBR | B4679: 0600.19.B BR - VALVULA COMPUERTA (ESCLUSA) BR 3/4" FV | E4679: https://res.cloudinary.com/riqra/image/upload/v1534706090/saas/resources/placeholders/product.png | F4679: 85 | G4679: 11.91 | H4679: =VLOOKUP(C4679,Categorias!B:C,2,FALSE) -> #N/A | I4679: =VLOOKUP(D4679,SubCategorias!B:C,2,FALSE) -> #N/A
A4680: 23200105AM | B4680: 23200105 AM - CABLE FLEXIBLE #14 THHN/THWN AMARILLO 100MTS INCABLE | E4680: https://res.cloudinary.com/riqra/image/upload/v1534706090/saas/resources/placeholders/product.png | F4680: 90 | G4680: 34.76 | H4680: =VLOOKUP(C4680,Categorias!B:C,2,FALSE) -> #N/A | I4680: =VLOOKUP(D4680,SubCategorias!B:C,2,FALSE) -> #N/A
A4681: CAN-PVC15X10 | B4681: CAN-PVC 15X10 - CANALETA ADHESIVA 15MMX10MMX2M PROW | E4681: https://res.cloudinary.com/riqra/image/upload/v1534706090/saas/resources/placeholders/product.png | F4681: 3505 | G4681: 0.77 | H4681: =VLOOKUP(C4681,Categorias!B:C,2,FALSE) -> #N/A | I4681: =VLOOKUP(D4681,SubCategorias!B:C,2,FALSE) -> #N/A
A4682: CAN-PVC20X10 | B4682: CAN-PVC 20X10 - CANALETA ADHESIVA 20MMX10MMX2M PROW | E4682: https://res.cloudinary.com/riqra/image/upload/v1534706090/saas/resources/placeholders/product.png | F4682: 4994 | G4682: 0.88 | H4682: =VLOOKUP(C4682,Categorias!B:C,2,FALSE) -> #N/A | I4682: =VLOOKUP(D4682,SubCategorias!B:C,2,FALSE) -> #N/A
A4683: CAN-PVC24X14 | B4683: CAN-PVC 24X14 - CANALETA ADHESIVA 24MMX14MMX2M PROW | E4683: https://res.cloudinary.com/riqra/image/upload/v1534706090/saas/resources/placeholders/product.png | F4683: 677 | G4683: 1.39 | H4683: =VLOOKUP(C4683,Categorias!B:C,2,FALSE) -> #N/A | I4683: =VLOOKUP(D4683,SubCategorias!B:C,2,FALSE) -> #N/A
A4684: CAN-PVC39X19 | B4684: CAN-PVC 39X19 - CANALETA ADHESIVA 39MMX19MMX2M PROW | E4684: https://res.cloudinary.com/riqra/image/upload/v1534706090/saas/resources/placeholders/product.png | F4684: 1007 | G4684: 1.97 | H4684: =VLOOKUP(C4684,Categorias!B:C,2,FALSE) -> #N/A | I4684: =VLOOKUP(D4684,SubCategorias!B:C,2,FALSE) -> #N/A
A4685: E103.15.27.0DH | B4685: E103.15.27.0 DH - CABEZA ALTA 15 LATERAL ARMADA FV | E4685: https://res.cloudinary.com/riqra/image/upload/v1534706090/saas/resources/placeholders/product.png | F4685: 22 | G4685: 10.34 | H4685: =VLOOKUP(C4685,Categorias!B:C,2,FALSE) -> #N/A | I4685: =VLOOKUP(D4685,SubCategorias!B:C,2,FALSE) -> #N/A
... A4789: 16030 | B4789: 16030 - # BISAGRA OMEGA LATONADA (PARES) | E4789: https://res.cloudinary.com/riqra/image/upload/v1534706090/saas/resources/placeholders/product.png | F4789: 0 | G4789: 0.88 | H4789: =VLOOKUP(C4789,Categorias!B:C,2,FALSE) -> #N/A | I4789: =VLOOKUP(D4789,SubCategorias!B:C,2,FALSE) -> #N/A
A4790: 17178 | B4790: 17178 - VALVULA COMPUERTA 1/2 RED WHITE | C4790: Plomería | D4790: Valvulas | E4790: https://res.cloudinary.com/riqra/image/upload/v1671052630/sellers/7/ociiqunmlgytwnqqf6ed.png | F4790: 13 | G4790: 12.61 | H4790: =VLOOKUP(C4790,Categorias!B:C,2,FALSE) -> 706 | I4790: =VLOOKUP(D4790,SubCategorias!B:C,2,FALSE) -> 0
A4791: 17179 | B4791: 17179 - VALVULA COMPUERTA 3/4 RED WHITE | C4791: Plomería | D4791: Valvulas | E4791: https://res.cloudinary.com/riqra/image/upload/v1671052630/sellers/8/ukqflt6xnpknb9wwrj1f.png | F4791: 17 | G4791: 17.62 | H4791: =VLOOKUP(C4791,Categorias!B:C,2,FALSE) -> 706 | I4791: =VLOOKUP(D4791,SubCategorias!B:C,2,FALSE) -> 0
A4792: 17180 | B4792: 17180 - VALVULA COMPUERTA 1 RED WHITE | C4792: Plomería | D4792: Valvulas | E4792: https://res.cloudinary.com/riqra/image/upload/v1671052630/sellers/9/wjre9whtvq8zzuksjmvs.png | F4792: 4 | G4792: 28.07 | H4792: =VLOOKUP(C4792,Categorias!B:C,2,FALSE) -> 706 | I4792: =VLOOKUP(D4792,SubCategorias!B:C,2,FALSE) -> 0
A4793: 17191 | B4793: 17191 - VALVULA CHEQUE HORIZONTAL 1/2 RED WHITE | C4793: Plomería | D4793: Valvulas | E4793: https://res.cloudinary.com/riqra/image/upload/v1671052630/sellers/10/alnmrh1kwofcywx6sj5r.png | F4793: 50 | G4793: 13.29 | H4793: =VLOOKUP(C4793,Categorias!B:C,2,FALSE) -> 706 | I4793: =VLOOKUP(D4793,SubCategorias!B:C,2,FALSE) -> 0
A4794: 17192 | B4794: 17192 - VALVULA CHEQUE HORIZONTAL 3/4 RED WHITE | C4794: Plomería | D4794: Valvulas | E4794: https://res.cloudinary.com/riqra/image/upload/v1671052630/sellers/11/fkzci92ijmkiek3jivlr.png | F4794: 2 | G4794: 19.17 | H4794: =VLOOKUP(C4794,Categorias!B:C,2,FALSE) -> 706 | I4794: =VLOOKUP(D4794,SubCategorias!B:C,2,FALSE) -> 0
A4795: 17193 | B4795: 17193 - VALVULA CHEQUE HORIZONTAL 1 RED WHITE | C4795: Plomería | D4795: Valvulas | E4795: https://res.cloudinary.com/riqra/image/upload/v1671052630/sellers/12/u86zce7gtdmxj4s6udh8.png | F4795: 0 | G4795: 29.75 | H4795: =VLOOKUP(C4795,Categorias!B:C,2,FALSE) -> 706 | I4795: =VLOOKUP(D4795,SubCategorias!B:C,2,FALSE) -> 0
A4796: 17303 | B4796: 17303 - CERRADURA SOBREPONER 50 MM 7502 VIRO | E4796: https://res.cloudinary.com/riqra/image/upload/v1671052630/sellers/13/tquetreakavtalntjlej.png | F4796: 10 | G4796: 42.51 | H4796: =VLOOKUP(C4796,Categorias!B:C,2,FALSE) -> #N/A | I4796: =VLOOKUP(D4796,SubCategorias!B:C,2,FALSE) -> #N/A
A4797: 17304 | B4797: 17304 - CERRADURA SOBREPONER 60 MM 7503 VIRO | E4797: https://res.cloudinary.com/riqra/image/upload/v1671052630/sellers/14/xq5hbrmdsu4rhrwg3rxf.png | F4797: 7 | G4797: 42.94 | H4797: =VLOOKUP(C4797,Categorias!B:C,2,FALSE) -> #N/A | I4797: =VLOOKUP(D4797,SubCategorias!B:C,2,FALSE) -> #N/A
A4798: 17388 | B4798: 17388 - CANDADO 20MM 551 FAI BY VIRO | E4798: https://res.cloudinary.com/riqra/image/upload/v1671052632/sellers/0/p1pa2d1py4piwfxzsg13.png | F4798: 24 | G4798: 3.67 | H4798: =VLOOKUP(C4798,Categorias!B:C,2,FALSE) -> #N/A | I4798: =VLOOKUP(D4798,SubCategorias!B:C,2,FALSE) -> #N/A
A4799: 17389 | B4799: 17389 - CANDADO 25MM 552 FAI BY VIRO | E4799: https://res.cloudinary.com/riqra/image/upload/v1671052632/sellers/1/yow05jkuebcaqcnr7yby.png | F4799: 42 | G4799: 3.67 | H4799: =VLOOKUP(C4799,Categorias!B:C,2,FALSE) -> #N/A | I4799: =VLOOKUP(D4799,SubCategorias!B:C,2,FALSE) -> #N/A
A4800: 17390 | B4800: 17390 - CANDADO 30MM 553 FAI BY VIRO | E4800: https://res.cloudinary.com/riqra/image/upload/v1534706090/saas/resources/placeholders/product.png | F4800: 12 | G4800: 5.78 | H4800: =VLOOKUP(C4800,Categorias!B:C,2,FALSE) -> #N/A | I4800: =VLOOKUP(D4800,SubCategorias!B:C,2,FALSE) -> #N/A
A4801: 17391 | B4801: 17391 - CANDADO 40MM 554 FAI BY VIRO | E4801: https://res.cloudinary.com/riqra/image/upload/v1671052632/sellers/2/qzvujptt8jgiqnhs3ehe.png | F4801: 0 | G4801: 7.92 | H4801: =VLOOKUP(C4801,Categorias!B:C,2,FALSE) -> #N/A | I4801: =VLOOKUP(D4801,SubCategorias!B:C,2,FALSE) -> #N/A
A4802: 17392 | B4802: 17392 - CANDADO 50MM 555 FAI BY VIRO | E4802: https://res.cloudinary.com/riqra/image/upload/v1671052632/sellers/3/vrsjil5hydalltrnzzoa.png | F4802: 20 | G4802: 15.34 | H4802: =VLOOKUP(C4802,Categorias!B:C,2,FALSE) -> #N/A | I4802: =VLOOKUP(D4802,SubCategorias!B:C,2,FALSE) -> #N/A
A4803: 17393 | B4803: 17393 - CANDADO 60MM 556 FAI BY VIRO | E4803: https://res.cloudinary.com/riqra/image/upload/v1671052632/sellers/4/gy9sj1vw8kclg8kqx1p7.png | F4803: 6 | G4803: 21.72 | H4803: =VLOOKUP(C4803,Categorias!B:C,2,FALSE) -> #N/A | I4803: =VLOOKUP(D4803,SubCategorias!B:C,2,FALSE) -> #N/A
A4804: 17394 | B4804: 17394 - CANDADO 70MM 557 FAI BY VIRO | E4804: https://res.cloudinary.com/riqra/image/upload/v1671052632/sellers/5/meqt2txld4bwhn83vseq.png | F4804: 0 | G4804: 27.10 | H4804: =VLOOKUP(C4804,Categorias!B:C,2,FALSE) -> #N/A | I4804: =VLOOKUP(D4804,SubCategorias!B:C,2,FALSE) -> #N/A
A4805: 21212 | B4805: 21212 - TORNILLO TRIPA DE PATO/COLEPATO CAB. AVELLANADA 12X11/2" (UNIDAD) | E4805: https://res.cloudinary.com/riqra/image/upload/v1534706090/saas/resources/placeholders/product.png | F4805: 300 | G4805: 0.19 | H4805: =VLOOKUP(C4805,Categorias!B:C,2,FALSE) -> #N/A | I4805: =VLOOKUP(D4805,SubCategorias!B:C,2,FALSE) -> #N/A
A4806: 22108 | B4806: 22108 - BREAKER ENCHUF. 1 POLO 15 AMP. 1/2 THQP115 GE | C4806: Material Eléctrico | D4806: Breakers | E4806: https://res.cloudinary.com/riqra/image/upload/v1671052632/sellers/6/hrgesvdkyco2iuxgogoh.png | F4806: 168 | G4806: 4.49 | H4806: =VLOOKUP(C4806,Categorias!B:C,2,FALSE) -> 694 | I4806: =VLOOKUP(D4806,SubCategorias!B:C,2,FALSE) -> 0
A4807: 22109 | B4807: 22109 - BREAKER ENCHUF. 1 POLO 20 AMP. 1/2 THQP120 GE | C4807: Material Eléctrico | D4807: Breakers | E4807: https://res.cloudinary.com/riqra/image/upload/v1671052632/sellers/7/jtkwlaiqrno73lbcgpcs.png | F4807: 100 | G4807: 4.49 | H4807: =VLOOKUP(C4807,Categorias!B:C,2,FALSE) -> 694 | I4807: =VLOOKUP(D4807,SubCategorias!B:C,2,FALSE) -> 0
A4808: 22110 | B4808: 22110 - BREAKER ENCHUF. 1 POLO 30 AMP. 1/2 THQP130 GE | C4808: Material Eléctrico | D4808: Breakers | E4808: https://res.cloudinary.com/riqra/image/upload/v1671052632/sellers/8/kc5by3cna5q5bobnzu67.png | F4808: 101 | G4808: 4.49 | H4808: =VLOOKUP(C4808,Categorias!B:C,2,FALSE) -> 694 | I4808: =VLOOKUP(D4808,SubCategorias!B:C,2,FALSE) -> 0
A4809: 22113 | B4809: 22113 - BREAKER ENCHUF. 2 POLO 20 AMP. 1/2 THQP220 GE | C4809: Material Eléctrico | D4809: Breakers | E4809: https://res.cloudinary.com/riqra/image/upload/v1671052632/sellers/9/tbbo8qc4ph0wae28bck2.png | F4809: 0 | G4809: 12.47 | H4809: =VLOOKUP(C4809,Categorias!B:C,2,FALSE) -> 694 | I4809: =VLOOKUP(D4809,SubCategorias!B:C,2,FALSE) -> 0
A4810: 22114 | B4810: 22114 - BREAKER ENCHUF. 2 POLO 30 AMP. 1/2 THQP230 GE | C4810: Material Eléctrico | D4810: Breakers | E4810: https://res.cloudinary.com/riqra/image/upload/v1671052632/sellers/10/ao2mj7znazewaawy3d1p.png | F4810: 0 | G4810: 12.35 | H4810: =VLOOKUP(C4810,Categorias!B:C,2,FALSE) -> 694 | I4810: =VLOOKUP(D4810,SubCategorias!B:C,2,FALSE) -> 0
A4811: 22118 | B4811: 22118 - BREAKER SBPTO. 1 POLO 20 AMP 1" TQC 220WL GE | C4811: Material Eléctrico | D4811: Breakers | E4811: https://res.cloudinary.com/riqra/image/upload/v1671052632/sellers/11/xwh43uz1qnyjvgeclxkq.png | F4811: 48 | G4811: 6.83 | H4811: =VLOOKUP(C4811,Categorias!B:C,2,FALSE) -> 694 | I4811: =VLOOKUP(D4811,SubCategorias!B:C,2,FALSE) -> 0
A4812: 22119 | B4812: 22119 - BREAKER SBPTO. 1 POLO 30 AMP 1" TQC 230WL GE | C4812: Material Eléctrico | D4812: Breakers | E4812: https://res.cloudinary.com/riqra/image/upload/v1671052632/sellers/12/ridbln0fbuqjybiwi181.png | F4812: 38 | G4812: 6.83 | H4812: =VLOOKUP(C4812,Categorias!B:C,2,FALSE) -> 694 | I4812: =VLOOKUP(D4812,SubCategorias!B:C,2,FALSE) -> 0
A4813: 22120 | B4813: 22120 - BREAKER SBPTO. 1 POLO 40 AMP 1" TQC 240WL GE | C4813: Material Eléctrico | D4813: Breakers | E4813: https://res.cloudinary.com/riqra/image/upload/v1671052632/sellers/13/xrbhremvkondc0mlo6ro.png | F4813: 48 | G4813: 7.15 | H4813: =VLOOKUP(C4813,Categorias!B:C,2,FALSE) -> 694 | I4813: =VLOOKUP(D4813,SubCategorias!B:C,2,FALSE) -> 0
A4814: 22121 | B4814: 22121 - BREAKER SBPTO. 1 POLO 50 AMP 1" TQC 250WL GE | C4814: Material Eléctrico | D4814: Breakers | E4814: https://res.cloudinary.com/riqra/image/upload/v1671052632/sellers/14/ywpobji3ep2776i8potn.png | F4814: 42 | G4814: 7.06 | H4814: =VLOOKUP(C4814,Categorias!B:C,2,FALSE) -> 694 | I4814: =VLOOKUP(D4814,SubCategorias!B:C,2,FALSE) -> 0
A4815: 22122 | B4815: 22122 - BREAKER SBPTO. 1 POLO 60 AMP 1" TQC 260WL GE | C4815: Material Eléctrico | D4815: Breakers | E4815: https://res.cloudinary.com/riqra/image/upload/v1671052634/sellers/0/mequmhxfefremwpvx0gx.png | F4815: 56 | G4815: 6.97 | H4815: =VLOOKUP(C4815,Categorias!B:C,2,FALSE) -> 694 | I4815: =VLOOKUP(D4815,SubCategorias!B:C,2,FALSE) -> 0
A4816: 22123 | B4816: 22123 - BREAKER SBPTO. 1 POLO 70 AMP 1" TQC 270WL GE | C4816: Material Eléctrico | D4816: Breakers | E4816: https://res.cloudinary.com/riqra/image/upload/v1671052634/sellers/1/jlta6xgubxjsiwvxagt0.png | F4816: 8 | G4816: 12.66 | H4816: =VLOOKUP(C4816,Categorias!B:C,2,FALSE) -> 694 | I4816: =VLOOKUP(D4816,SubCategorias!B:C,2,FALSE) -> 0
A4817: 22125 | B4817: 22125 - BREAKER SBPTO. 2 POLO 15 AMP 1" TQC 2415WL GE | C4817: Material Eléctrico | D4817: Breakers | E4817: https://res.cloudinary.com/riqra/image/upload/v1671052634/sellers/2/iaxjinx8us29bd78rjrz.png | F4817: 20 | G4817: 16.72 | H4817: =VLOOKUP(C4817,Categorias!B:C,2,FALSE) -> 694 | I4817: =VLOOKUP(D4817,SubCategorias!B:C,2,FALSE) -> 0
... A4824: 22150 | B4824: 22150 - CAJA PARA BREAKER 8-16 1/2 TLM812FCUD GE | C4824: Material Eléctrico | D4824: Breakers | E4824: https://res.cloudinary.com/riqra/image/upload/v1671052634/sellers/9/yglwe48qdjhji8ifhz7e.png | F4824: 0 | G4824: 44.10 | H4824: =VLOOKUP(C4824,Categorias!B:C,2,FALSE) -> 694 | I4824: =VLOOKUP(D4824,SubCategorias!B:C,2,FALSE) -> 0
A4825: 23762 | B4825: 23762 - # PIEAMIGO O MENSULA DE 5X7 NEGRA VERA(PAR) | E4825: https://res.cloudinary.com/riqra/image/upload/v1666371253/sellers/4/p5e6oxcmikghzxfnohdm.png | F4825: 0 | G4825: 2.31 | H4825: =VLOOKUP(C4825,Categorias!B:C,2,FALSE) -> #N/A | I4825: =VLOOKUP(D4825,SubCategorias!B:C,2,FALSE) -> #N/A
A4826: 24406 | B4826: 24406 - # ESCUDO JALA/AMER.C/MAN. ZAMAC LATONADA | E4826: https://res.cloudinary.com/riqra/image/upload/v1534706090/saas/resources/placeholders/product.png | F4826: 0 | G4826: 2.55 | H4826: =VLOOKUP(C4826,Categorias!B:C,2,FALSE) -> #N/A | I4826: =VLOOKUP(D4826,SubCategorias!B:C,2,FALSE) -> #N/A
A4827: 24414 | B4827: 24414 - # MANIJA ARABE DE ZAMAC NO 1 CROMADA | E4827: https://res.cloudinary.com/riqra/image/upload/v1534706090/saas/resources/placeholders/product.png | F4827: 0 | G4827: 1.03 | H4827: =VLOOKUP(C4827,Categorias!B:C,2,FALSE) -> #N/A | I4827: =VLOOKUP(D4827,SubCategorias!B:C,2,FALSE) -> #N/A
A4828: 30809 | B4828: 30809 - # TIRADERA DE ZAMAC 88MM CROMADA | E4828: https://res.cloudinary.com/riqra/image/upload/v1534706090/saas/resources/placeholders/product.png | F4828: 0 | G4828: 0.28 | H4828: =VLOOKUP(C4828,Categorias!B:C,2,FALSE) -> #N/A | I4828: =VLOOKUP(D4828,SubCategorias!B:C,2,FALSE) -> #N/A
A4829: 30817 | B4829: 30817 - # TIRADERA DE ZAMAC 88MM DORADA | E4829: https://res.cloudinary.com/riqra/image/upload/v1534706090/saas/resources/placeholders/product.png | F4829: 0 | G4829: 0.28 | H4829: =VLOOKUP(C4829,Categorias!B:C,2,FALSE) -> #N/A | I4829: =VLOOKUP(D4829,SubCategorias!B:C,2,FALSE) -> #N/A
A4830: 30858 | B4830: 30858 - # TIRADERA DE ZAMAC 97MM CROMADA | E4830: https://res.cloudinary.com/riqra/image/upload/v1534706090/saas/resources/placeholders/product.png | F4830: 0 | G4830: 0.30 | H4830: =VLOOKUP(C4830,Categorias!B:C,2,FALSE) -> #N/A | I4830: =VLOOKUP(D4830,SubCategorias!B:C,2,FALSE) -> #N/A
A4831: 30866 | B4831: 30866 - # TIRADERA DE ZAMAC 97MM DORADA | E4831: https://res.cloudinary.com/riqra/image/upload/v1534706090/saas/resources/placeholders/product.png | F4831: 0 | G4831: 0.30 | H4831: =VLOOKUP(C4831,Categorias!B:C,2,FALSE) -> #N/A | I4831: =VLOOKUP(D4831,SubCategorias!B:C,2,FALSE) -> #N/A
A4832: 31194 | B4832: 31194 - PLAFON ENSAMBLADO CON RETIE ROMA | E4832: https://res.cloudinary.com/riqra/image/upload/v1534706090/saas/resources/placeholders/product.png | F4832: 6000 | G4832: 0.56 | H4832: =VLOOKUP(C4832,Categorias!B:C,2,FALSE) -> #N/A | I4832: =VLOOKUP(D4832,SubCategorias!B:C,2,FALSE) -> #N/A
A4833: 32211 | B4833: 32211 - MANGUERA P/GAS/AIRE IND. 5/16 DE 8MM 100MT (420SI) NEGRA | E4833: https://res.cloudinary.com/riqra/image/upload/v1666371253/sellers/5/vunwz7psabqxgdl8rfql.png | F4833: 5 | G4833: 77.34 | H4833: =VLOOKUP(C4833,Categorias!B:C,2,FALSE) -> #N/A | I4833: =VLOOKUP(D4833,SubCategorias!B:C,2,FALSE) -> #N/A
A4834: 50515 | B4834: 50515 - # SUBCAJ LVP SENC GALAX CROMO LLAVE | E4834: https://res.cloudinary.com/riqra/image/upload/v1534706090/saas/resources/placeholders/product.png | F4834: 0 | G4834: 7.53 | H4834: =VLOOKUP(C4834,Categorias!B:C,2,FALSE) -> #N/A | I4834: =VLOOKUP(D4834,SubCategorias!B:C,2,FALSE) -> #N/A
A4835: 53231 | B4835: 53231 - #EXTENSION 1 SERVICIO NARANJA 3X16 AWG 25 PIES | E4835: https://res.cloudinary.com/riqra/image/upload/v1534706090/saas/resources/placeholders/product.png | F4835: 207 | G4835: 5.13 | H4835: =VLOOKUP(C4835,Categorias!B:C,2,FALSE) -> #N/A | I4835: =VLOOKUP(D4835,SubCategorias!B:C,2,FALSE) -> #N/A
A4836: 59100 | B4836: 59100 - # MEZCLADOR VENTO LAVAMANOS 8 | E4836: https://res.cloudinary.com/riqra/image/upload/v1534706090/saas/resources/placeholders/product.png | F4836: 0 | G4836: 13.32 | H4836: =VLOOKUP(C4836,Categorias!B:C,2,FALSE) -> #N/A | I4836: =VLOOKUP(D4836,SubCategorias!B:C,2,FALSE) -> #N/A
... A4854: 60693 | B4854: 60693 - ESPACIADOR PARA NIVELACION 1.0MM (FUNX50UND) CORTAG | E4854: https://res.cloudinary.com/riqra/image/upload/v1534706090/saas/resources/placeholders/product.png | F4854: 1071 | G4854: 3.09 | H4854: =VLOOKUP(C4854,Categorias!B:C,2,FALSE) -> #N/A | I4854: =VLOOKUP(D4854,SubCategorias!B:C,2,FALSE) -> #N/A
A4855: 60694 | B4855: 60694 - CUÑA PARA NIVELAR PISO FUNDAX50UN CORTAG | C4855: Acabados | D4855: Instalación | E4855: https://res.cloudinary.com/riqra/image/upload/v1668364911/sellers/0/fddyqcrgj4mokkxly7mc.png | F4855: 0 | G4855: 5.72 | H4855: =VLOOKUP(C4855,Categorias!B:C,2,FALSE) -> 690 | I4855: =VLOOKUP(D4855,SubCategorias!B:C,2,FALSE) -> #N/A
A4856: 60695 | B4856: 60695 - ALICATE PARA NIVELAR PISO CORTAG | E4856: https://res.cloudinary.com/riqra/image/upload/v1534706090/saas/resources/placeholders/product.png | F4856: 0 | G4856: 15.47 | H4856: =VLOOKUP(C4856,Categorias!B:C,2,FALSE) -> #N/A | I4856: =VLOOKUP(D4856,SubCategorias!B:C,2,FALSE) -> #N/A
A4857: 60850 | B4857: 60850 - RASPADOR DE JUNTAS STANDART CORTAG | E4857: https://res.cloudinary.com/riqra/image/upload/v1671052636/sellers/5/l3ofcgltrdpmv0pmfqcy.png | F4857: 10 | G4857: 6.01 | H4857: =VLOOKUP(C4857,Categorias!B:C,2,FALSE) -> #N/A | I4857: =VLOOKUP(D4857,SubCategorias!B:C,2,FALSE) -> #N/A
A4858: 60881 | B4858: 60881 - BROCA DIAMANTADA 35MM CORTAG | E4858: https://res.cloudinary.com/riqra/image/upload/v1671052636/sellers/6/yvlbvcuqdtby4xkmfmk0.png | F4858: 12 | G4858: 21.52 | H4858: =VLOOKUP(C4858,Categorias!B:C,2,FALSE) -> #N/A | I4858: =VLOOKUP(D4858,SubCategorias!B:C,2,FALSE) -> #N/A
A4859: 60886 | B4859: 60886 - BROCA DIAMANTADA 10MM CORTAG | E4859: https://res.cloudinary.com/riqra/image/upload/v1671052636/sellers/7/ehvknj813hqv4jzbnxbq.png | F4859: 1 | G4859: 9.53 | H4859: =VLOOKUP(C4859,Categorias!B:C,2,FALSE) -> #N/A | I4859: =VLOOKUP(D4859,SubCategorias!B:C,2,FALSE) -> #N/A
A4860: 60950 | B4860: 60950 - ESPUMA DE POLIRETANO EXPANDIDO CORTAG | C4860: Acabados | D4860: Instalación | E4860: https://res.cloudinary.com/riqra/image/upload/v1668364911/sellers/1/zpntjboz9mbepejcpzsx.png | F4860: 17 | G4860: 1.59 | H4860: =VLOOKUP(C4860,Categorias!B:C,2,FALSE) -> 690 | I4860: =VLOOKUP(D4860,SubCategorias!B:C,2,FALSE) -> #N/A
A4861: 60958 | B4861: 60958 - LLANA ACERO DIENTE 10 1/8" 8X8MM CORTAG | E4861: https://res.cloudinary.com/riqra/image/upload/v1534706090/saas/resources/placeholders/product.png | F4861: 0 | G4861: 3.48 | H4861: =VLOOKUP(C4861,Categorias!B:C,2,FALSE) -> #N/A | I4861: =VLOOKUP(D4861,SubCategorias!B:C,2,FALSE) -> #N/A
A4862: 60960 | B4862: 60960 - LLANA ACERO DIENTE 10 1/8" 10X10MM CORTAG | E4862: https://res.cloudinary.com/riqra/image/upload/v1534706090/saas/resources/placeholders/product.png | F4862: 7 | G4862: 3.48 | H4862: =VLOOKUP(C4862,Categorias!B:C,2,FALSE) -> #N/A | I4862: =VLOOKUP(D4862,SubCategorias!B:C,2,FALSE) -> #N/A
A4863: 60962 | B4863: 60962 - LANA LISA 25.6X 12CM CORTAG | E4863: https://res.cloudinary.com/riqra/image/upload/v1671052636/sellers/8/sqtekzcuqebavttcgcik.png | F4863: 0 | G4863: 3.48 | H4863: =VLOOKUP(C4863,Categorias!B:C,2,FALSE) -> #N/A | I4863: =VLOOKUP(D4863,SubCategorias!B:C,2,FALSE) -> #N/A
A4864: 60998 | B4864: 60998 - LANA DE DENTADA 10X10MM-38CM CORTAG | E4864: https://res.cloudinary.com/riqra/image/upload/v1671052636/sellers/9/ah90l7or69lin3aign5i.png | F4864: 2 | G4864: 4.37 | H4864: =VLOOKUP(C4864,Categorias!B:C,2,FALSE) -> #N/A | I4864: =VLOOKUP(D4864,SubCategorias!B:C,2,FALSE) -> #N/A
A4865: 61276 | B4865: 61276 - MARTILLO NEGRO 80MM CORTAG | E4865: https://res.cloudinary.com/riqra/image/upload/v1534706090/saas/resources/placeholders/product.png | F4865: 4 | G4865: 8.82 | H4865: =VLOOKUP(C4865,Categorias!B:C,2,FALSE) -> #N/A | I4865: =VLOOKUP(D4865,SubCategorias!B:C,2,FALSE) -> #N/A
A4866: 61279 | B4866: 61279 - MARTILLO BLANCO 80MM CORTAG | E4866: https://res.cloudinary.com/riqra/image/upload/v1534706090/saas/resources/placeholders/product.png | F4866: 5 | G4866: 8.86 | H4866: =VLOOKUP(C4866,Categorias!B:C,2,FALSE) -> #N/A | I4866: =VLOOKUP(D4866,SubCategorias!B:C,2,FALSE) -> #N/A
A4867: 61293 | B4867: 61293 - RODEL UNIVERSAL TITANIO 18MM-100MM CORTAG | E4867: https://res.cloudinary.com/riqra/image/upload/v1534706090/saas/resources/placeholders/product.png | F4867: 8 | G4867: 16.29 | H4867: =VLOOKUP(C4867,Categorias!B:C,2,FALSE) -> #N/A | I4867: =VLOOKUP(D4867,SubCategorias!B:C,2,FALSE) -> #N/A
A4868: 61296 | B4868: 61296 - ESPACIADO PARA NIVELACION 2MM (FUNX50UND) CORTAG | E4868: https://res.cloudinary.com/riqra/image/upload/v1534706090/saas/resources/placeholders/product.png | F4868: 151 | G4868: 3.09 | H4868: =VLOOKUP(C4868,Categorias!B:C,2,FALSE) -> #N/A | I4868: =VLOOKUP(D4868,SubCategorias!B:C,2,FALSE) -> #N/A
A4869: 61307 | B4869: 61307 - SEPARADOR CRUCETAS TIPO CRUZ 1"MM PARA JUNTAS (FUNX100UND) CORTAG | C4869: Acabados | D4869: Instalación | E4869: https://res.cloudinary.com/riqra/image/upload/v1668364911/sellers/2/gofyzhetybqzhxqwuf9h.png | F4869: 57 | G4869: 1.28 | H4869: =VLOOKUP(C4869,Categorias!B:C,2,FALSE) -> 690 | I4869: =VLOOKUP(D4869,SubCategorias!B:C,2,FALSE) -> #N/A
A4870: 61308 | B4870: 61308 - SEPARADOR CRUCETAS Y "T" 1.5MM PARA JUNTAS (FUNX100UND) CORTAG | C4870: Acabados | D4870: Instalación | E4870: https://res.cloudinary.com/riqra/image/upload/v1668364911/sellers/3/exw6ukcdj8e9yinp5qak.png | F4870: 15 | G4870: 1.28 | H4870: =VLOOKUP(C4870,Categorias!B:C,2,FALSE) -> 690 | I4870: =VLOOKUP(D4870,SubCategorias!B:C,2,FALSE) -> #N/A
A4871: 61309 | B4871: 61309 - SEPARADOR CRUCETAS Y "T" 3MM PARA JUNTAS (FUNX100UND) CORTAG | C4871: Acabados | D4871: Instalación | E4871: https://res.cloudinary.com/riqra/image/upload/v1671052636/sellers/10/ih0tvigsqdczkm7wpnih.png | F4871: 0 | G4871: 1.28 | H4871: =VLOOKUP(C4871,Categorias!B:C,2,FALSE) -> 690 | I4871: =VLOOKUP(D4871,SubCategorias!B:C,2,FALSE) -> #N/A
A4872: 61315 | B4872: 61315 - SEPARADOR CRUCETAS Y "T" 2MM PARA JUNTAS (FUNX100UND) CORTAG | C4872: Acabados | D4872: Instalación | E4872: https://res.cloudinary.com/riqra/image/upload/v1668364911/sellers/5/m0gewiwuliiefk1t5oj1.png | F4872: 0 | G4872: 1.28 | H4872: =VLOOKUP(C4872,Categorias!B:C,2,FALSE) -> 690 | I4872: =VLOOKUP(D4872,SubCategorias!B:C,2,FALSE) -> #N/A
A4873: 61336 | B4873: 61336 - ESPACIADOR PARA NIVELACION 1.5MM ROJO (FUNX50UND) CORTAG | E4873: https://res.cloudinary.com/riqra/image/upload/v1534706090/saas/resources/placeholders/product.png | F4873: 0 | G4873: 2.35 | H4873: =VLOOKUP(C4873,Categorias!B:C,2,FALSE) -> #N/A | I4873: =VLOOKUP(D4873,SubCategorias!B:C,2,FALSE) -> #N/A
A4874: 61350 | B4874: 61350 - RODEL UNIVERSAL WIDIA 7MM-80MM CORTAG | C4874: Acabados | D4874: Instalación | E4874: https://res.cloudinary.com/riqra/image/upload/v1668364911/sellers/6/m34kanhweljwznkljpax.png | F4874: 48 | G4874: 4.56 | H4874: =VLOOKUP(C4874,Categorias!B:C,2,FALSE) -> 690 | I4874: =VLOOKUP(D4874,SubCategorias!B:C,2,FALSE) -> #N/A
A4875: 61353 | B4875: 61353 - LANA DE DENTADA 12X12MM-48CM CORTAG | E4875: https://res.cloudinary.com/riqra/image/upload/v1671052636/sellers/11/ja2rt6t6cot7r3ncdatp.png | F4875: 2 | G4875: 5.62 | H4875: =VLOOKUP(C4875,Categorias!B:C,2,FALSE) -> #N/A | I4875: =VLOOKUP(D4875,SubCategorias!B:C,2,FALSE) -> #N/A
A4876: 61364 | B4876: 61364 - RASPADOR DE JUNTA-LAMINA 1.3MM CORTAG | E4876: https://res.cloudinary.com/riqra/image/upload/v1671052636/sellers/12/rfgalij9rlmk5izyfpo6.png | F4876: 0 | G4876: 4.65 | H4876: =VLOOKUP(C4876,Categorias!B:C,2,FALSE) -> #N/A | I4876: =VLOOKUP(D4876,SubCategorias!B:C,2,FALSE) -> #N/A
A4877: 61365 | B4877: 61365 - CORTADOR PROF. CERAMICA Y PORCELANATO 62CMX45X45CMX12MM CORTAG | E4877: https://res.cloudinary.com/riqra/image/upload/v1534706090/saas/resources/placeholders/product.png | F4877: 20 | G4877: 121.87 | H4877: =VLOOKUP(C4877,Categorias!B:C,2,FALSE) -> #N/A | I4877: =VLOOKUP(D4877,SubCategorias!B:C,2,FALSE) -> #N/A
A4878: 61554 | B4878: 61554 - SEPARADOR CRUCETAS Y "T" 1MM PARA JUNTAS (FUNX100UND) CORTAG | C4878: Acabados | D4878: Instalación | E4878: https://res.cloudinary.com/riqra/image/upload/v1671052636/sellers/13/qyht0jzzo4yl9ilskkot.png | F4878: 39 | G4878: 1.28 | H4878: =VLOOKUP(C4878,Categorias!B:C,2,FALSE) -> 690 | I4878: =VLOOKUP(D4878,SubCategorias!B:C,2,FALSE) -> #N/A
A4879: 61562 | B4879: 61562 - MEZCLADORA ELECTRICO HM -140 127V CORTAG | E4879: https://res.cloudinary.com/riqra/image/upload/v1671052636/sellers/14/kk9967lmi2pzwhvhvmge.png | F4879: 2 | G4879: 187.38 | H4879: =VLOOKUP(C4879,Categorias!B:C,2,FALSE) -> #N/A | I4879: =VLOOKUP(D4879,SubCategorias!B:C,2,FALSE) -> #N/A
A4880: 61589 | B4880: 61589 - SOPORTE REGULABLE PARA REGLA 50CM R61589 CORTAG | E4880: https://res.cloudinary.com/riqra/image/upload/v1671052639/sellers/0/g1otvfp4pwaifcuqnnml.png | F4880: 0 | G4880: 25.03 | H4880: =VLOOKUP(C4880,Categorias!B:C,2,FALSE) -> #N/A | I4880: =VLOOKUP(D4880,SubCategorias!B:C,2,FALSE) -> #N/A
A4881: 61660 | B4881: 61660 - RODEL UNIVERSAL WIDIA 10MM-100MM CORTAG | E4881: https://res.cloudinary.com/riqra/image/upload/v1534706090/saas/resources/placeholders/product.png | F4881: 32 | G4881: 10.66 | H4881: =VLOOKUP(C4881,Categorias!B:C,2,FALSE) -> #N/A | I4881: =VLOOKUP(D4881,SubCategorias!B:C,2,FALSE) -> #N/A
A4882: 61661 | B4882: 61661 - RODEL UNIVERSAL TITANIO 10MM-100MM CORTAG | C4882: Acabados | D4882: Instalación | E4882: https://res.cloudinary.com/riqra/image/upload/v1668364911/sellers/8/uajj9zhzplfsklomshz2.png | F4882: 8 | G4882: 11.47 | H4882: =VLOOKUP(C4882,Categorias!B:C,2,FALSE) -> 690 | I4882: =VLOOKUP(D4882,SubCategorias!B:C,2,FALSE) -> #N/A
A4883: 61662 | B4883: 61662 - RODEL UNIVERSAL WIDIA 7MM-100MM CORTAG | E4883: https://res.cloudinary.com/riqra/image/upload/v1534706090/saas/resources/placeholders/product.png | F4883: 10 | G4883: 7.29 | H4883: =VLOOKUP(C4883,Categorias!B:C,2,FALSE) -> #N/A | I4883: =VLOOKUP(D4883,SubCategorias!B:C,2,FALSE) -> #N/A
A4884: 61783 | B4884: 61783 - LLANA DE ACERO INOX DENTADA 10X10MM MANGO BI-COMPONETE CERRADA CORTAG | E4884: https://res.cloudinary.com/riqra/image/upload/v1671052638/sellers/1/x81oxkhzqhfqnhsml2qg.png | F4884: 4 | G4884: 8.15 | H4884: =VLOOKUP(C4884,Categorias!B:C,2,FALSE) -> #N/A | I4884: =VLOOKUP(D4884,SubCategorias!B:C,2,FALSE) -> #N/A
A4885: 61784 | B4885: 61784 - LLANA DE ACERO INOX DENTADA 12X12MM-MANGO BI-COMPONETE CERRADO CORTAG | E4885: https://res.cloudinary.com/riqra/image/upload/v1671052638/sellers/2/xsw4z9odv19ydiqgomqq.png | F4885: 0 | G4885: 8.15 | H4885: =VLOOKUP(C4885,Categorias!B:C,2,FALSE) -> #N/A | I4885: =VLOOKUP(D4885,SubCategorias!B:C,2,FALSE) -> #N/A
...

Sheet Categorias
A1: Cod | B1: Categorias
A2: 1 | B2: Material Eléctrico | C2: 694
A3: 2 | B3: Acabados | C3: 690
A4: 3 | B4: Construcción | C4: 703
A5: 4 | B5: Pinturas y complementos | C5: 705
A6: 5 | B6: Seguridad Industrial | C6: 704
A7: 6 | B7: Herramientas Manuales | C7: 741
A8: 7 | B8: Cerrajería | C8: 701
A9: 8 | B9: Plomería | C9: 706
A10: 9 | B10: Ferretería | C10: 742
A11: 10 | B11: Limpieza | C11: 743
A12: 11 | B12: Herramientas eléctricas & Accesorios | C12: 702
A13: 12 | B13: Automotriz | C13: 744
... A15: 14 | B15: Gypsum & Tumbados | C15: 746

Sheet SubCategorias
A1: Codigo | B1: SubCategoria | C1: Relacion
A2: 1 | B2: Cables | C2: 1
A3: 2 | B3: Ceramica de piso
A4: 3 | B4: Impermeabilizantes
A5: 4 | B5: Empastes
A6: 5 | B6: Brochas
A7: 6 | B7: Guantes
A8: 7 | B8: Otros
A9: 8 | B9: Tubería Conduit Metálica (EMT)
A10: 9 | B10: Palas
A11: 10 | B11: Limas
A12: 11 | B12: Llaves
A13: 12 | B13: Tomacorrientes
A14: 13 | B14: Pomos
... A181: 180 | B181: Cabos|Ferretería

Sheet Relacion
A1: Relacion | B1: Cat | C1: Sub
A2: =VLOOKUP(B2,Categorias!B:C,2,FALSE) -> 690 | B2: Acabados | C2: Bloque de Vidrio
A3: =VLOOKUP(B3,Categorias!B:C,2,FALSE) -> 690 | B3: Acabados | C3: Ceramica de pared
A4: =VLOOKUP(B4,Categorias!B:C,2,FALSE) -> 690 | B4: Acabados | C4: Ceramica de piso
A5: =VLOOKUP(B5,Categorias!B:C,2,FALSE) -> 690 | B5: Acabados | C5: Duchas Electricas
A6: =VLOOKUP(B6,Categorias!B:C,2,FALSE) -> 690 | B6: Acabados | C6: Fregaderos
A7: =VLOOKUP(B7,Categorias!B:C,2,FALSE) -> 690 | B7: Acabados | C7: Granito
A8: =VLOOKUP(B8,Categorias!B:C,2,FALSE) -> 690 | B8: Acabados | C8: Griferia
A9: =VLOOKUP(B9,Categorias!B:C,2,FALSE) -> 690 | B9: Acabados | C9: Lavamanos
A10: =VLOOKUP(B10,Categorias!B:C,2,FALSE) -> 690 | B10: Acabados | C10: Porcelana para empore
A11: =VLOOKUP(B11,Categorias!B:C,2,FALSE) -> 690 | B11: Acabados | C11: Porcelanato
A12: =VLOOKUP(B12,Categorias!B:C,2,FALSE) -> 690 | B12: Acabados | C12: Rejillas
A13: =VLOOKUP(B13,Categorias!B:C,2,FALSE) -> 690 | B13: Acabados | C13: Sanitarios
... A236: =VLOOKUP(B236,Categorias!B:C,2,FALSE) -> 704 | B236: Seguridad Industrial | C236: Guantes
